[
  {
    "type": "constructor",
    "inputs": [],
    "stateMutability": "nonpayable"
  },
  {
    "type": "receive",
    "stateMutability": "payable"
  },
  {
    "name": "GUARDIAN",
    "type": "function",
    "inputs": [],
    "outputs": [
      {
        "name": "",
        "type": "address",
        "internalType": "address"
      }
    ],
    "stateMutability": "view"
  },
  {
    "name": "L2_ORACLE",
    "type": "function",
    "inputs": [],
    "outputs": [
      {
        "name": "",
        "type": "address",
        "internalType": "contract L2OutputOracle"
      }
    ],
    "stateMutability": "view"
  },
  {
    "name": "SYSTEM_CONFIG",
    "type": "function",
    "inputs": [],
    "outputs": [
      {
        "name": "",
        "type": "address",
        "internalType": "contract SystemConfig"
      }
    ],
    "stateMutability": "view"
  },
  {
    "name": "depositTransaction",
    "type": "function",
    "inputs": [
      {
        "name": "_to",
        "type": "address",
        "internalType": "address"
      },
      {
        "name": "_value",
        "type": "uint256",
        "internalType": "uint256"
      },
      {
        "name": "_gasLimit",
        "type": "uint64",
        "internalType": "uint64"
      },
      {
        "name": "_isCreation",
        "type": "bool",
        "internalType": "bool"
      },
      {
        "name": "_data",
        "type": "bytes",
        "internalType": "bytes"
      }
    ],
    "outputs": [],
    "stateMutability": "payable"
  },
  {
    "name": "donateETH",
    "type": "function",
    "inputs": [],
    "outputs": [],
    "stateMutability": "payable"
  },
  {
    "name": "finalizeWithdrawalTransaction",
    "type": "function",
    "inputs": [
      {
        "name": "_tx",
        "type": "tuple",
        "components": [
          {
            "name": "nonce",
            "type": "uint256",
            "internalType": "uint256"
          },
          {
            "name": "sender",
            "type": "address",
            "internalType": "address"
          },
          {
            "name": "target",
            "type": "address",
            "internalType": "address"
          },
          {
            "name": "value",
            "type": "uint256",
            "internalType": "uint256"
          },
          {
            "name": "gasLimit",
            "type": "uint256",
            "internalType": "uint256"
          },
          {
            "name": "data",
            "type": "bytes",
            "internalType": "bytes"
          }
        ],
        "internalType": "struct Types.WithdrawalTransaction"
      }
    ],
    "outputs": [],
    "stateMutability": "nonpayable"
  },
  {
    "name": "finalizedWithdrawals",
    "type": "function",
    "inputs": [
      {
        "name": "",
        "type": "bytes32",
        "internalType": "bytes32"
      }
    ],
    "outputs": [
      {
        "name": "",
        "type": "bool",
        "internalType": "bool"
      }
    ],
    "stateMutability": "view"
  },
  {
    "name": "guardian",
    "type": "function",
    "inputs": [],
    "outputs": [
      {
        "name": "",
        "type": "address",
        "internalType": "address"
      }
    ],
    "stateMutability": "view"
  },
  {
    "name": "initialize",
    "type": "function",
    "inputs": [
      {
        "name": "_l2Oracle",
        "type": "address",
        "internalType": "contract L2OutputOracle"
      },
      {
        "name": "_guardian",
        "type": "address",
        "internalType": "address"
      },
      {
        "name": "_systemConfig",
        "type": "address",
        "internalType": "contract SystemConfig"
      },
      {
        "name": "_paused",
        "type": "bool",
        "internalType": "bool"
      }
    ],
    "outputs": [],
    "stateMutability": "nonpayable"
  },
  {
    "name": "isOutputFinalized",
    "type": "function",
    "inputs": [
      {
        "name": "_l2OutputIndex",
        "type": "uint256",
        "internalType": "uint256"
      }
    ],
    "outputs": [
      {
        "name": "",
        "type": "bool",
        "internalType": "bool"
      }
    ],
    "stateMutability": "view"
  },
  {
    "name": "l2Oracle",
    "type": "function",
    "inputs": [],
    "outputs": [
      {
        "name": "",
        "type": "address",
        "internalType": "contract L2OutputOracle"
      }
    ],
    "stateMutability": "view"
  },
  {
    "name": "l2Sender",
    "type": "function",
    "inputs": [],
    "outputs": [
      {
        "name": "",
        "type": "address",
        "internalType": "address"
      }
    ],
    "stateMutability": "view"
  },
  {
    "name": "minimumGasLimit",
    "type": "function",
    "inputs": [
      {
        "name": "_byteCount",
        "type": "uint64",
        "internalType": "uint64"
      }
    ],
    "outputs": [
      {
        "name": "",
        "type": "uint64",
        "internalType": "uint64"
      }
    ],
    "stateMutability": "pure"
  },
  {
    "name": "params",
    "type": "function",
    "inputs": [],
    "outputs": [
      {
        "name": "prevBaseFee",
        "type": "uint128",
        "internalType": "uint128"
      },
      {
        "name": "prevBoughtGas",
        "type": "uint64",
        "internalType": "uint64"
      },
      {
        "name": "prevBlockNum",
        "type": "uint64",
        "internalType": "uint64"
      }
    ],
    "stateMutability": "view"
  },
  {
    "name": "pause",
    "type": "function",
    "inputs": [],
    "outputs": [],
    "stateMutability": "nonpayable"
  },
  {
    "name": "paused",
    "type": "function",
    "inputs": [],
    "outputs": [
      {
        "name": "",
        "type": "bool",
        "internalType": "bool"
      }
    ],
    "stateMutability": "view"
  },
  {
    "name": "proveWithdrawalTransaction",
    "type": "function",
    "inputs": [
      {
        "name": "_tx",
        "type": "tuple",
        "components": [
          {
            "name": "nonce",
            "type": "uint256",
            "internalType": "uint256"
          },
          {
            "name": "sender",
            "type": "address",
            "internalType": "address"
          },
          {
            "name": "target",
            "type": "address",
            "internalType": "address"
          },
          {
            "name": "value",
            "type": "uint256",
            "internalType": "uint256"
          },
          {
            "name": "gasLimit",
            "type": "uint256",
            "internalType": "uint256"
          },
          {
            "name": "data",
            "type": "bytes",
            "internalType": "bytes"
          }
        ],
        "internalType": "struct Types.WithdrawalTransaction"
      },
      {
        "name": "_l2OutputIndex",
        "type": "uint256",
        "internalType": "uint256"
      },
      {
        "name": "_outputRootProof",
        "type": "tuple",
        "components": [
          {
            "name": "version",
            "type": "bytes32",
            "internalType": "bytes32"
          },
          {
            "name": "stateRoot",
            "type": "bytes32",
            "internalType": "bytes32"
          },
          {
            "name": "messagePasserStorageRoot",
            "type": "bytes32",
            "internalType": "bytes32"
          },
          {
            "name": "latestBlockhash",
            "type": "bytes32",
            "internalType": "bytes32"
          }
        ],
        "internalType": "struct Types.OutputRootProof"
      },
      {
        "name": "_withdrawalProof",
        "type": "bytes[]",
        "internalType": "bytes[]"
      }
    ],
    "outputs": [],
    "stateMutability": "nonpayable"
  },
  {
    "name": "provenWithdrawals",
    "type": "function",
    "inputs": [
      {
        "name": "",
        "type": "bytes32",
        "internalType": "bytes32"
      }
    ],
    "outputs": [
      {
        "name": "outputRoot",
        "type": "bytes32",
        "internalType": "bytes32"
      },
      {
        "name": "timestamp",
        "type": "uint128",
        "internalType": "uint128"
      },
      {
        "name": "l2OutputIndex",
        "type": "uint128",
        "internalType": "uint128"
      }
    ],
    "stateMutability": "view"
  },
  {
    "name": "systemConfig",
    "type": "function",
    "inputs": [],
    "outputs": [
      {
        "name": "",
        "type": "address",
        "internalType": "contract SystemConfig"
      }
    ],
    "stateMutability": "view"
  },
  {
    "name": "unpause",
    "type": "function",
    "inputs": [],
    "outputs": [],
    "stateMutability": "nonpayable"
  },
  {
    "name": "version",
    "type": "function",
    "inputs": [],
    "outputs": [
      {
        "name": "",
        "type": "string",
        "internalType": "string"
      }
    ],
    "stateMutability": "view"
  },
  {
    "name": "Initialized",
    "type": "event",
    "inputs": [
      {
        "name": "version",
        "type": "uint8",
        "indexed": false,
        "internalType": "uint8"
      }
    ],
    "anonymous": false
  },
  {
    "name": "Paused",
    "type": "event",
    "inputs": [
      {
        "name": "account",
        "type": "address",
        "indexed": false,
        "internalType": "address"
      }
    ],
    "anonymous": false
  },
  {
    "name": "TransactionDeposited",
    "type": "event",
    "inputs": [
      {
        "name": "from",
        "type": "address",
        "indexed": true,
        "internalType": "address"
      },
      {
        "name": "to",
        "type": "address",
        "indexed": true,
        "internalType": "address"
      },
      {
        "name": "version",
        "type": "uint256",
        "indexed": true,
        "internalType": "uint256"
      },
      {
        "name": "opaqueData",
        "type": "bytes",
        "indexed": false,
        "internalType": "bytes"
      }
    ],
    "anonymous": false
  },
  {
    "name": "Unpaused",
    "type": "event",
    "inputs": [
      {
        "name": "account",
        "type": "address",
        "indexed": false,
        "internalType": "address"
      }
    ],
    "anonymous": false
  },
  {
    "name": "WithdrawalFinalized",
    "type": "event",
    "inputs": [
      {
        "name": "withdrawalHash",
        "type": "bytes32",
        "indexed": true,
        "internalType": "bytes32"
      },
      {
        "name": "success",
        "type": "bool",
        "indexed": false,
        "internalType": "bool"
      }
    ],
    "anonymous": false
  },
  {
    "name": "WithdrawalProven",
    "type": "event",
    "inputs": [
      {
        "name": "withdrawalHash",
        "type": "bytes32",
        "indexed": true,
        "internalType": "bytes32"
      },
      {
        "name": "from",
        "type": "address",
        "indexed": true,
        "internalType": "address"
      },
      {
        "name": "to",
        "type": "address",
        "indexed": true,
        "internalType": "address"
      }
    ],
    "anonymous": false
  }
]